odoo/addons/contract_refund_on_stop/README.rst
odoo/addons/contract_refund_on_stop/__init__.py
odoo/addons/contract_refund_on_stop/__manifest__.py
odoo/addons/contract_refund_on_stop/i18n/contract_refund_on_stop.pot
odoo/addons/contract_refund_on_stop/i18n/fr.po
odoo/addons/contract_refund_on_stop/i18n/it.po
odoo/addons/contract_refund_on_stop/i18n/nl.po
odoo/addons/contract_refund_on_stop/models/__init__.py
odoo/addons/contract_refund_on_stop/models/contract_line.py
odoo/addons/contract_refund_on_stop/models/res_company.py
odoo/addons/contract_refund_on_stop/models/res_config_settings.py
odoo/addons/contract_refund_on_stop/readme/CONFIGURE.md
odoo/addons/contract_refund_on_stop/readme/CONTEXT.md
odoo/addons/contract_refund_on_stop/readme/CONTRIBUTORS.md
odoo/addons/contract_refund_on_stop/readme/DESCRIPTION.md
odoo/addons/contract_refund_on_stop/readme/USAGE.md
odoo/addons/contract_refund_on_stop/static/description/icon.png
odoo/addons/contract_refund_on_stop/static/description/index.html
odoo/addons/contract_refund_on_stop/tests/__init__.py
odoo/addons/contract_refund_on_stop/tests/test_contract_refund.py
odoo/addons/contract_refund_on_stop/views/res_config_settings.xml
odoo_addon_contract_refund_on_stop-18.0.1.0.0.8.dist-info/METADATA
odoo_addon_contract_refund_on_stop-18.0.1.0.0.8.dist-info/WHEEL
odoo_addon_contract_refund_on_stop-18.0.1.0.0.8.dist-info/top_level.txt
odoo_addon_contract_refund_on_stop-18.0.1.0.0.8.dist-info/RECORD
